odoo10_addon_pos_pricelist-10.0.1.0.5-py3.8-nspkg.pth
odoo/addons/pos_pricelist/README.rst
odoo/addons/pos_pricelist/__init__.py
odoo/addons/pos_pricelist/__manifest__.py
odoo/addons/pos_pricelist/hooks.py
odoo/addons/pos_pricelist/i18n/ca.po
odoo/addons/pos_pricelist/i18n/es.po
odoo/addons/pos_pricelist/i18n/fr.po
odoo/addons/pos_pricelist/i18n/hr_HR.po
odoo/addons/pos_pricelist/i18n/it.po
odoo/addons/pos_pricelist/i18n/nl_NL.po
odoo/addons/pos_pricelist/i18n/pos_pricelist.pot
odoo/addons/pos_pricelist/models/__init__.py
odoo/addons/pos_pricelist/models/pos_config.py
odoo/addons/pos_pricelist/models/pos_order.py
odoo/addons/pos_pricelist/models/res_partner.py
odoo/addons/pos_pricelist/security/ir.model.access.csv
odoo/addons/pos_pricelist/static/description/icon.png
odoo/addons/pos_pricelist/static/src/js/models.js
odoo/addons/pos_pricelist/static/src/js/screens.js
odoo/addons/pos_pricelist/static/src/xml/pos.xml
odoo/addons/pos_pricelist/templates/assets.xml
odoo/addons/pos_pricelist/views/pos_config_view.xml
odoo10_addon_pos_pricelist-10.0.1.0.5.dist-info/METADATA
odoo10_addon_pos_pricelist-10.0.1.0.5.dist-info/WHEEL
odoo10_addon_pos_pricelist-10.0.1.0.5.dist-info/namespace_packages.txt
odoo10_addon_pos_pricelist-10.0.1.0.5.dist-info/top_level.txt
odoo10_addon_pos_pricelist-10.0.1.0.5.dist-info/RECORD
